tfdlpack-0.1.3.data/purelib/tfdlpack/__init__.py
tfdlpack-0.1.3.data/purelib/tfdlpack/capsule_api.py
tfdlpack-0.1.3.data/purelib/tfdlpack/core.py
tfdlpack-0.1.3.data/purelib/tfdlpack/libinfo.py
tfdlpack-0.1.3.data/purelib/tfdlpack/libtfdlpack-tf-2.1.0.so
tfdlpack-0.1.3.data/purelib/tfdlpack/libtfdlpack-tf-2.2.0.so
tfdlpack-0.1.3.dist-info/METADATA
tfdlpack-0.1.3.dist-info/RECORD
tfdlpack-0.1.3.dist-info/WHEEL
tfdlpack-0.1.3.dist-info/top_level.txt
